sin.v
`ifndef SIN_V
`define SIN_V

module sin_fixed #(
    parameter ITER = 7  // 可選項數，建議不要超過 100
)(
    input  wire signed [31:0] x,   // Q16.16 格式輸入
    output reg  signed [31:0] y    // Q16.16 格式輸出 sin(x)
);

    integer i;
    reg signed [63:0] term;
    reg signed [63:0] num;         // x^n（分子）
    reg signed [63:0] factorial;   // n!（分母）
    reg signed [63:0] sum;
    reg sign;

    always @(*) begin
        sum = x;         // sin(x) = x - x³/3! + x⁵/5! - ...
        sign = 1'b1;     // 下一項是 -x³/3!
        num = (x * x) >>> 16;       // x²
        num = (num * x) >>> 16;     // x³
        factorial = 64'd6;          // 3!

        for (i = 1; i < ITER; i = i + 1) begin
            term = num / factorial;

            if (sign)
                sum = sum - term;
            else
                sum = sum + term;

            // num = num * x²
            num = (num * ((x * x) >>> 16)) >>> 16;

            // factorial *= (2i+2)(2i+3)
            factorial = factorial * (2 * i + 2);
            factorial = factorial * (2 * i + 3);

            sign = ~sign;
        end

        y = sum[31:0];  // 回傳 Q16.16 格式
    end

endmodule

`endif

cos.v
`ifndef COS_V
`define COS_V

module cos_fixed #(
    parameter ITER = 7 // 建議不要超過 100，避免溢位和過度延遲
)(
    input  wire signed [31:0] x,   // Q16.16 弧度輸入
    output reg  signed [31:0] y    // Q16.16 cos(x)
);

    integer i;
    reg signed [63:0] term;
    reg signed [63:0] num;         // 分子 x^n
    reg signed [63:0] factorial;   // 分母 n!
    reg signed [63:0] one;         // 1.0 (Q16.16)
    reg signed [63:0] sum;
    reg sign;

    always @(*) begin
        one = 64'sd1 << 16;
        sum = one;      // y = 1
        sign = 1'b1;    // 第一個項是 -x²/2!
        num = (x * x) >> 16;  // x²
        factorial = 64'd2;
        //$display(" x_input=%0f",  x);
        for (i = 1; i < ITER; i = i + 1) begin
            term = num / factorial;

            if (sign)
                sum = sum - term;
            else
                sum = sum + term;

            // 更新下一項：num = num * x² (Q16.16)
            num = (num * ((x * x) >>> 16)) >>> 16;

            // 更新 factorial：n *= (2i+1)(2i+2)
            factorial = factorial * (2 * i + 1);
            factorial = factorial * (2 * i + 2);

            sign = ~sign;
        end

        y = sum[31:0];  // 轉回 Q16.16 結果
    end

endmodule

`endif

bit_reverse.v
`ifndef BIT_REVERSE_V
`define BIT_REVERSE_V
`define WIDTH 32

module bit_reverse (
    input  wire [31:0] b,    // 要進行 bit reverse 的輸入值
    input  wire [31:0] m,    // 要反轉幾個 bit (例如 log2(N))
    output reg  [31:0] result
);

    integer i;
    reg [31:0]b1;

    always @(*) begin
        result = 0;
        for (i = 0; i < m; i = i + 1) begin
            b1=(b >> i) & 32'd1;
            result = result | (b1 << ((m - 1) - i));
        end
    end

endmodule
`endif

pi.v
`ifndef PI_V
`define PI_V
`define WIDTH 32

	module pi 
		#(parameter w=`WIDTH)
		(
			output reg[w-1:0] pi
		);
		
		reg signed [31:0]sign;//sign need array
		reg signed [31:0] i;
		reg signed [31:0] iter;
		reg signed [31:0] domin;
	
		initial begin
			sign=1;
			i=0;
			iter=2000;
			pi = (1 << 16);  // 正確，表示 1.0 in Q16.16
			domin=1;
			while(i <iter) begin
				domin=domin+2;
				sign=-sign;
				pi=pi+sign*((1<<<16)/domin);
				i=i+1;
			end
			pi=pi*4;
		end
	endmodule
`endif

log2.v
`ifndef LOG2_V
`define LOG2_V
`define WIDTH 32
 module log2
 	#(parameter W=`WIDTH)
 	(
 		input wire [W-1:0] N_in,
 		output reg [W-1:0] log2
  
 	);
	reg [W-1:0] N; 
	always @(*) begin
		N=N_in;
		log2=0;
		while(N>>1) begin
			N=N>>1;
			log2 = log2 + 1;
		end
	end
 endmodule  
`endif

complex.v
	// =====================================================
	// complex.v  (Verilog-2001)
	//   - complex_add : (a_re + jb_im) + (c_re + jd_im)
	//   - complex_mul : (a + jb) × (c + jd)
	// -----------------------------------------------------
	// ★ 整數定點示例：   WIDTH = 16 → Q15.0
	//   要用浮點(IP)時，把乘法換成 fp_multiplier 即可
	// =====================================================

	`ifndef COMPLEX_V
	`define COMPLEX_V

	// ---------- 可調參數 -----------------
	`define WIDTH 32               // 單一實、虛部位寬

	// ---------- 加法 ---------------------
	module complex_add
	#(parameter W=`WIDTH)
	(
	    input  signed [W-1:0] a_re, a_im,
	    input  signed [W-1:0] b_re, b_im,
	    output signed [W-1:0] c_re, c_im
	);
	    assign c_re = a_re + b_re;
	    assign c_im = a_im + b_im;
	endmodule

	//-----------sub-----------------------
	module complex_sub
	#(parameter W=`WIDTH)
	(
	    input  signed [W-1:0] a_re, a_im,
	    input  signed [W-1:0] b_re, b_im,
	    output signed [W-1:0] c_re, c_im
	);
	    assign c_re = a_re -b_re;
	    assign c_im = a_im - b_im;
	endmodule
	// ---------- 乘法 ---------------------
	// re = ar*br - ai*bi
	// im = ar*bi + ai*br
	// ------------------------ complex_mul ------------------------
	module complex_mul #(parameter W = 32)(
	    input  signed [W-1:0] a_re, a_im,
	    input  signed [W-1:0] b_re, b_im,
	    output signed [W-1:0] c_re,
	    output signed [W-1:0] c_im
	);
	    // 乘完先保持 64bit 精度
	wire signed [63:0] p_re = a_re * b_re - a_im * b_im;
	wire signed [63:0] p_im = a_re * b_im + a_im * b_re;
	
    	    // Q16.16 → 回到原位寬，這裡做四捨五入
	wire signed [63:0] p_re_rnd = p_re + 32'sd32768;   // +0.5
    	wire signed [63:0] p_im_rnd = p_im + 32'sd32768;

    	assign c_re = p_re_rnd[47:16];  // >>16（取 31..16）
    	assign c_im = p_im_rnd[47:16];
endmodule


	`endif

fft.v
//=============================
// fft.v
//=============================
`ifndef FFT_V
`define FFT_V
`timescale 1ns/1ps

`include "complex.v"
`include "log2.v"
`include "pi.v"
`include "bit_reverse.v"
`include "sin.v"
`include "cos.v"

`define WIDTH 32

module fft #(parameter w=`WIDTH) (
    input wire clk,
    input wire rst,
    input wire start,
    input wire [31:0] x_Re[0:7],
    input wire [31:0] x_Im[0:7],
    input wire [31:0] N,
    output reg [31:0] FFT,
    output reg done
);
    integer k, i, j, b;
    reg signed [31:0] Theta_T,Theta_T1, phi_T_Re, phi_T_Im, T_Re, T_Im, temp_Re, temp_Im;
    reg signed [31:0] x_Re_reg[0:7];
    reg signed [31:0] x_Im_reg[0:7];
    reg signed [31:0] pi_D;
    	

    integer ii,a, m, n;

    wire  signed[31:0] y_cos1, y_sin1;
    wire signed [31:0] add_Re, add_Im, sub_Re, sub_Im;
    wire  signed[31:0] mul1_Re, mul1_Im, mul2_Re, mul2_Im;
    wire signed [31:0] log2_out, pi_out, bit_reverse_out;

    reg [3:0] state;
    localparam IDLE=0, LOAD=1, CALC=2, DONE=3;

    complex_add u_add(.a_re(x_Re_reg[j]), .a_im(x_Im_reg[j]),
                      .b_re(x_Re_reg[b]), .b_im(x_Im_reg[b]),
                      .c_re(add_Re), .c_im(add_Im));
    complex_sub u_sub(.a_re(x_Re_reg[j]), .a_im(x_Im_reg[j]),
                      .b_re(x_Re_reg[b]), .b_im(x_Im_reg[b]),
                      .c_re(sub_Re), .c_im(sub_Im));
    complex_mul u_mul1(.a_re(T_Re), .a_im(T_Im),
                       .b_re(phi_T_Re), .b_im(phi_T_Im),
                       .c_re(mul1_Re), .c_im(mul1_Im));
    complex_mul u_mul2(.a_re(temp_Re), .a_im(temp_Im),
                       .b_re(T_Re), .b_im(T_Im),
                       .c_re(mul2_Re), .c_im(mul2_Im));
    log2 u_log(.N_in(N), .log2(log2_out));
    pi u_pi(.pi(pi_out));
    bit_reverse u_bit_reverse(.b(b), .m(m), .result(bit_reverse_out));
    cos_fixed u_cos1(.x(Theta_T), .y(y_cos1));
    sin_fixed u_sin2(.x(Theta_T), .y(y_sin1));

    always @(posedge clk or posedge rst) begin
        if (rst) begin
             done <= 0;
             FFT <= 0;
             state <= IDLE;
             pi_D = 0;
             m=0;
             Theta_T =0;
             Theta_T1 =0;
             phi_T_Re=0;
             phi_T_Im=0;	
             T_Re=1;
             T_Im=0;
        end else begin
            case (state)
                IDLE: if (start) begin
                	 state <= LOAD;
			 	
             		end
                LOAD: begin
                    for (ii = 0; ii < 8; ii = ii + 1) begin
                        x_Re_reg[ii] = x_Re[ii];
                        x_Im_reg[ii] = x_Im[ii];
                        //$display(" input_x_Re=%0f",  x_Re_reg[ii] );
                       // $display(" input_x_Im=%0f",  x_Im_reg[ii] );
                    end
                    state <= CALC;
                end

                CALC: begin
                    k = N;
                     	//$display("start");
                     	//$display("statte=%0d",state);
                    while (k > 1) begin
                    	
                    	//$display("pi_out=%0f", pi_out/65536.0	);
                        //$display("N=%0f", N );
                        
                       
		
                        n = k;
                        k = k >> 1;
                        pi_D=pi_out;
                        //$display("pi_D=%0f", pi_D/65536.0);
                        Theta_T= ((pi_out) / n)<<1;
		        #10
                        $display("Theta_T = %0f", Theta_T / 65536.0);
	    		
                        phi_T_Re = y_cos1;
                        phi_T_Im = -y_sin1;
                        //$display(" phi_T_Re=%0f",  phi_T_Re/65536.0);
                        //$display(" phi_T_Im=%0f",  phi_T_Im/65536.0);
                        T_Re=32'sd65536;//65536.0
                        T_Im=32'sd0;
                        //$display(" T_Re2=%0f",  T_Re);
			//$display(" T_Im2=%0f",  T_Im);
                        for (i = 0; i < k; i = i + 1) begin
                            for (j = i; j < N; j = j + n) begin
                                b = j + k;
                                #10
                                temp_Re = sub_Re;
                                temp_Im = sub_Im;
                                
                   		//$display("sub temp_Re=%0f,temp_Im=%0f", temp_Re/65536.0,temp_Im/65536.0);
		      		
		      		#10
                                x_Re_reg[j] = add_Re;
                                x_Im_reg[j] = add_Im;
                                
                   		//$display("add x_Re_reg[%0d]=%0f,x_Im_reg[%0d]=%0f",j,   x_Re_reg[j]/65536.0,j,x_Im_reg[j]/65536.0);
		      		
		      		#10
                                x_Re_reg[b] = mul2_Re;
                                #10
                                x_Im_reg[b] = mul2_Im;
                                
                   		//$display("mul x_Re_reg[%0d]=%0f,x_Im_reg[%0d]=%0f",b,   x_Re_reg[b]/65536.0,b,x_Im_reg[b]/65536.0);
		      	
                            end
                            T_Re = mul1_Re;                            
                            T_Im = mul1_Im;
                            //$display(" fin_Re=%0f,fin_Im=%0f",   T_Re/65536.0,T_Im/65536.0);
			   
                        end
                        m = log2_out;
                        #10
                        //$display(" m=%0f", m);
                        for (a = 0; a < N; a = a + 1) begin
                            b=a;
                        #10
                            b = bit_reverse_out;
                            	
		    	    
                        #10
                            if (b > a) begin
                                temp_Re = x_Re_reg[a];                                
                                temp_Im = x_Im_reg[a];                                
                                x_Re_reg[a] = x_Re_reg[b];
                                x_Im_reg[a] = x_Im_reg[b];                                
                                x_Re_reg[b] = temp_Re;                              
                                x_Im_reg[b] = temp_Im;
                            end
                        end
                    end
                    for(i=0;i<N;i++) begin
                    $display(" final: x_Re_reg[%0d]=%0f,x_Im_reg[%0d]=%0f",i,   x_Re_reg[i]/65536.0,i,x_Im_reg[i]/65536.0);
		
		    end
		    #10
                    FFT <= x_Re_reg[0];
                    done <= 1;
                    state <= DONE;
                end

                DONE: ; // 保持狀態直到重置
            endcase
        end
    end
endmodule

`endif

complex_tb.v
`timescale 1ns/1ps
`include "complex.v"
`include "log2.v"
`include "pi.v"
`include "bit_reverse.v"
`include "fft.v"
`include "cos.v"
`include "sin.v"

module complex_tb;
    parameter NUM = 8;

    // 基本變數
    reg  signed [31:0] a_re, a_im, b_re, b_im;
    reg  [31:0] N;
    wire [31:0] log2;
    wire [31:0] pi;
    wire signed [31:0] add_re, add_im;
    wire signed [31:0] sub_re, sub_im;
    wire signed [31:0] mul_re, mul_im;
    reg  [31:0] b, m;
    wire [31:0] result;

    // Cos/Sin 測試
    reg signed [31:0] x;             // Q16.16
    wire signed [31:0] y_cos, y_sin; // Q16.16 輸出
    localparam signed [31:0] Q2   = 32'sd131072; // 2.0
    // FFT 測試
    reg clk = 0;
    reg rst;
    reg start;
    reg [31:0] x_Re[0:NUM-1];
    reg [31:0] x_Im[0:NUM-1];
    reg [31:0] N_fft;
    wire [31:0] FFT;
    wire done;

    // 時脈產生 (100 MHz)i
    always #5 clk = ~clk;
	
    // === 模組例化 ===
    complex_add u_add(.a_re(a_re), .a_im(a_im), .b_re(b_re), .b_im(b_im), .c_re(add_re), .c_im(add_im));
    complex_sub u_sub(.a_re(a_re), .a_im(a_im), .b_re(b_re), .b_im(b_im), .c_re(sub_re), .c_im(sub_im));
    complex_mul u_mul(.a_re(a_re), .a_im(a_im), .b_re(b_re), .b_im(b_im), .c_re(mul_re), .c_im(mul_im));
    log2        u_log(.N_in(N), .log2(log2));
    pi          u_pi(.pi(pi));
    bit_reverse u_bit_reverse(.b(b), .m(m), .result(result));
    //cos_fixed   u_cos(.x(x), .y(y_cos));
    //sin_fixed   u_sin(.x(x), .y(y_sin));

    fft u_fft(
        .clk(clk), .rst(rst), .start(start),
        .x_Re(x_Re), .x_Im(x_Im), .N(N_fft),
        .FFT(FFT), .done(done)
    );

    // === test bench ===
    initial begin
        $dumpfile("wave.vcd");
        $dumpvars(0, complex_tb);

        // === complex unit ===
        a_re = 	32'sd85197; a_im = 32'sd117964 ;   // 3 + j4
        b_re = 	32'sd91750 ; b_im = 32'sd131072 ;   // 1 + j2
        b = 32'd5; m = 32'd5;
        N = 32'd32;

        // === FFT data output ===
        x_Re[0] = 32'sd65536;  x_Re[1] = 32'sd65536;
        x_Re[2] = 32'sd65536; x_Re[3] = 32'sd65536;
        x_Re[4] = 32'sd0;        x_Re[5] = 32'sd0;
        x_Re[6] = 32'sd0;        x_Re[7] = 32'sd0;

        x_Im[0] = 32'sd0; x_Im[1] =32'sd0; x_Im[2] = 32'sd0; x_Im[3] =32'sd0;
        x_Im[4] = 32'sd0; x_Im[5] =32'sd0; x_Im[6] = 32'sd0; x_Im[7] = 32'sd0;

        // === control FFT ===
        N_fft = 32'sd8;
        rst = 1; start = 0;
        #20 rst = 0;
        #40 start = 1;

        // === test cos/sin ===
        //x = 32'sd51472; // 約等於 pi/3 ≈ 1.57 rad ≈ Q16.16 = 0x19220

        wait(done); // 等 FFT 完成

        // === show single module===
        //$display("FFT result: %d", FFT);
        //$display("ADD: (%0f , %0f)", add_re/65536.0, add_im/65536.0);
        //$display("SUB: (%0f , %0f)", sub_re/65536.0, sub_im/65536.0);
      	//$display("MUL: (%0f , %0f)", $itor(mul_re) / 65536.0,$itor(mul_im) / 65536.0);

        //$display("log(%0d) = %0d", N, log2);
        //$display("π (Q16.16) raw = %0d", pi);
        //$display("π ≈ %f", pi / 65536.0);
        //$display("bit reverse: %0f", result);
        //  $display("cos(%f) ≈ %f", x / 65536.0, y_cos / 65536.0);
        //$display("sin(%f) ≈ %f", x / 65536.0, y_sin / 65536.0);

        #100 $finish;
    end
endmodule

wave.vcd
$date
	Tue May 13 02:02:35 2025
$end
$version
	Icarus Verilog
$end
$timescale
	1ps
$end
$scope module complex_tb $end
$var wire 32 ! sub_re [31:0] $end
$var wire 32 " sub_im [31:0] $end
$var wire 32 # result [31:0] $end
$var wire 32 $ pi [31:0] $end
$var wire 32 % mul_re [31:0] $end
$var wire 32 & mul_im [31:0] $end
$var wire 32 ' log2 [31:0] $end
$var wire 1 ( done $end
$var wire 32 ) add_re [31:0] $end
$var wire 32 * add_im [31:0] $end
$var wire 32 + FFT [31:0] $end
$var parameter 32 , NUM $end
$var reg 32 - N [31:0] $end
$var reg 32 . N_fft [31:0] $end
$var reg 32 / a_im [31:0] $end
$var reg 32 0 a_re [31:0] $end
$var reg 32 1 b [31:0] $end
$var reg 32 2 b_im [31:0] $end
$var reg 32 3 b_re [31:0] $end
$var reg 1 4 clk $end
$var reg 32 5 m [31:0] $end
$var reg 1 6 rst $end
$var reg 1 7 start $end
$scope module u_add $end
$var wire 32 8 a_im [31:0] $end
$var wire 32 9 a_re [31:0] $end
$var wire 32 : b_im [31:0] $end
$var wire 32 ; b_re [31:0] $end
$var wire 32 < c_re [31:0] $end
$var wire 32 = c_im [31:0] $end
$var parameter 32 > W $end
$upscope $end
$scope module u_bit_reverse $end
$var wire 32 ? b [31:0] $end
$var wire 32 @ m [31:0] $end
$var reg 32 A b1 [31:0] $end
$var reg 32 B result [31:0] $end
$var integer 32 C i [31:0] $end
$upscope $end
$scope module u_fft $end
$var wire 32 D N [31:0] $end
$var wire 1 4 clk $end
$var wire 1 6 rst $end
$var wire 1 7 start $end
$var wire 32 E y_sin1 [31:0] $end
$var wire 32 F y_cos1 [31:0] $end
$var wire 32 G sub_Re [31:0] $end
$var wire 32 H sub_Im [31:0] $end
$var wire 32 I pi_out [31:0] $end
$var wire 32 J mul2_Re [31:0] $end
$var wire 32 K mul2_Im [31:0] $end
$var wire 32 L mul1_Re [31:0] $end
$var wire 32 M mul1_Im [31:0] $end
$var wire 32 N log2_out [31:0] $end
$var wire 32 O bit_reverse_out [31:0] $end
$var wire 32 P add_Re [31:0] $end
$var wire 32 Q add_Im [31:0] $end
$var parameter 32 R CALC $end
$var parameter 32 S DONE $end
$var parameter 32 T IDLE $end
$var parameter 32 U LOAD $end
$var parameter 32 V w $end
$var reg 32 W FFT [31:0] $end
$var reg 32 X T_Im [31:0] $end
$var reg 32 Y T_Re [31:0] $end
$var reg 32 Z Theta_T [31:0] $end
$var reg 32 [ Theta_T1 [31:0] $end
$var reg 1 ( done $end
$var reg 32 \ phi_T_Im [31:0] $end
$var reg 32 ] phi_T_Re [31:0] $end
$var reg 32 ^ pi_D [31:0] $end
$var reg 4 _ state [3:0] $end
$var reg 32 ` temp_Im [31:0] $end
$var reg 32 a temp_Re [31:0] $end
$var integer 32 b a [31:0] $end
$var integer 32 c b [31:0] $end
$var integer 32 d i [31:0] $end
$var integer 32 e ii [31:0] $end
$var integer 32 f j [31:0] $end
$var integer 32 g k [31:0] $end
$var integer 32 h m [31:0] $end
$var integer 32 i n [31:0] $end
$scope module u_add $end
$var wire 32 j a_im [31:0] $end
$var wire 32 k a_re [31:0] $end
$var wire 32 l b_im [31:0] $end
$var wire 32 m b_re [31:0] $end
$var wire 32 n c_re [31:0] $end
$var wire 32 o c_im [31:0] $end
$var parameter 32 p W $end
$upscope $end
$scope module u_bit_reverse $end
$var wire 32 q b [31:0] $end
$var wire 32 r m [31:0] $end
$var reg 32 s b1 [31:0] $end
$var reg 32 t result [31:0] $end
$var integer 32 u i [31:0] $end
$upscope $end
$scope module u_cos1 $end
$var wire 32 v x [31:0] $end
$var parameter 32 w ITER $end
$var reg 64 x factorial [63:0] $end
$var reg 64 y num [63:0] $end
$var reg 64 z one [63:0] $end
$var reg 1 { sign $end
$var reg 64 | sum [63:0] $end
$var reg 64 } term [63:0] $end
$var reg 32 ~ y [31:0] $end
$var integer 32 !" i [31:0] $end
$upscope $end
$scope module u_log $end
$var wire 32 "" N_in [31:0] $end
$var parameter 32 #" W $end
$var reg 32 $" N [31:0] $end
$var reg 32 %" log2 [31:0] $end
$upscope $end
$scope module u_mul1 $end
$var wire 32 &" a_im [31:0] $end
$var wire 32 '" a_re [31:0] $end
$var wire 32 (" b_im [31:0] $end
$var wire 32 )" b_re [31:0] $end
$var wire 64 *" p_re_rnd [63:0] $end
$var wire 64 +" p_re [63:0] $end
$var wire 64 ," p_im_rnd [63:0] $end
$var wire 64 -" p_im [63:0] $end
$var wire 32 ." c_re [31:0] $end
$var wire 32 /" c_im [31:0] $end
$var parameter 32 0" W $end
$upscope $end
$scope module u_mul2 $end
$var wire 32 1" a_im [31:0] $end
$var wire 32 2" a_re [31:0] $end
$var wire 32 3" b_im [31:0] $end
$var wire 32 4" b_re [31:0] $end
$var wire 64 5" p_re_rnd [63:0] $end
$var wire 64 6" p_re [63:0] $end
$var wire 64 7" p_im_rnd [63:0] $end
$var wire 64 8" p_im [63:0] $end
$var wire 32 9" c_re [31:0] $end
$var wire 32 :" c_im [31:0] $end
$var parameter 32 ;" W $end
$upscope $end
$scope module u_pi $end
$var parameter 32 <" w $end
$var reg 32 =" domin [31:0] $end
$var reg 32 >" i [31:0] $end
$var reg 32 ?" iter [31:0] $end
$var reg 32 @" pi [31:0] $end
$var reg 32 A" sign [31:0] $end
$upscope $end
$scope module u_sin2 $end
$var wire 32 B" x [31:0] $end
$var parameter 32 C" ITER $end
$var reg 64 D" factorial [63:0] $end
$var reg 64 E" num [63:0] $end
$var reg 1 F" sign $end
$var reg 64 G" sum [63:0] $end
$var reg 64 H" term [63:0] $end
$var reg 32 I" y [31:0] $end
$var integer 32 J" i [31:0] $end
$upscope $end
$scope module u_sub $end
$var wire 32 K" a_im [31:0] $end
$var wire 32 L" a_re [31:0] $end
$var wire 32 M" b_im [31:0] $end
$var wire 32 N" b_re [31:0] $end
$var wire 32 O" c_re [31:0] $end
$var wire 32 P" c_im [31:0] $end
$var parameter 32 Q" W $end
$upscope $end
$upscope $end
$scope module u_log $end
$var wire 32 R" N_in [31:0] $end
$var parameter 32 S" W $end
$var reg 32 T" N [31:0] $end
$var reg 32 U" log2 [31:0] $end
$upscope $end
$scope module u_mul $end
$var wire 32 V" a_im [31:0] $end
$var wire 32 W" a_re [31:0] $end
$var wire 32 X" b_im [31:0] $end
$var wire 32 Y" b_re [31:0] $end
$var wire 64 Z" p_re_rnd [63:0] $end
$var wire 64 [" p_re [63:0] $end
$var wire 64 \" p_im_rnd [63:0] $end
$var wire 64 ]" p_im [63:0] $end
$var wire 32 ^" c_re [31:0] $end
$var wire 32 _" c_im [31:0] $end
$var parameter 32 `" W $end
$upscope $end
$scope module u_pi $end
$var parameter 32 a" w $end
$var reg 32 b" domin [31:0] $end
$var reg 32 c" i [31:0] $end
$var reg 32 d" iter [31:0] $end
$var reg 32 e" pi [31:0] $end
$var reg 32 f" sign [31:0] $end
$upscope $end
$scope module u_sub $end
$var wire 32 g" a_im [31:0] $end
$var wire 32 h" a_re [31:0] $end
$var wire 32 i" b_im [31:0] $end
$var wire 32 j" b_re [31:0] $end
$var wire 32 k" c_re [31:0] $end
$var wire 32 l" c_im [31:0] $end
$var parameter 32 m" W $end
$upscope $end
$upscope $end
$enddefinitions $end
$comment Show the parameter values. $end
$dumpall
b100000 m"
b100000 a"
b100000 `"
b100000 S"
b100000 Q"
b111 C"
b100000 <"
b100000 ;"
b100000 0"
b100000 #"
b111 w
b100000 p
b100000 V
b1 U
b0 T
b11 S
b10 R
b100000 >
b1000 ,
$end
#0
$dumpvars
b11111111111111111100110011001100 l"
b11111111111111111110011001100111 k"
b10110011001100110 j"
b100000000000000000 i"
b10100110011001101 h"
b11100110011001100 g"
b1 f"
b110010010000111100 e"
b11111010000 d"
b11111010000 c"
b111110100001 b"
b1010001111010110111 _"
b11111111111111100011100001010011 ^"
b10100011110101101101110000101001000 ]"
b10100011110101101110110000101001000 \"
b1111111111111111111111111111111000111000010100110100011110101110 ["
b1111111111111111111111111111111000111000010100111100011110101110 Z"
b10110011001100110 Y"
b100000000000000000 X"
b10100110011001101 W"
b11100110011001100 V"
b101 U"
b1 T"
b100000 R"
bx P"
bx O"
bx N"
bx M"
bx L"
bx K"
b111 J"
b0 I"
b0 H"
b0 G"
1F"
b0 E"
b10011000001110111011101110101100000000000 D"
b0 B"
b1 A"
b110010010000111100 @"
b11111010000 ?"
b11111010000 >"
b111110100001 ="
bx :"
bx 9"
bx 8"
bx 7"
bx 6"
bx 5"
b1 4"
b0 3"
bx 2"
bx 1"
b0 /"
b0 ."
b0 -"
b1000000000000000 ,"
b0 +"
b1000000000000000 *"
b0 )"
b0 ("
b1 '"
b0 &"
b11 %"
b1 $"
b1000 ""
b111 !"
b10000000000000000 ~
b0 }
b10000000000000000 |
1{
b10000000000000000 z
b0 y
b1010001001100001110110010100000000000 x
b0 v
b0 u
b0 t
bx s
b0 r
bx q
bx o
bx n
bx m
bx l
bx k
bx j
bx i
b0 h
bx g
bx f
bx e
bx d
bx c
bx b
bx a
bx `
b0 _
b0 ^
b0 ]
b0 \
b0 [
b0 Z
b1 Y
b0 X
b0 W
bx Q
bx P
b0 O
b11 N
b0 M
b0 L
bx K
bx J
b110010010000111100 I
bx H
bx G
b10000000000000000 F
b0 E
b1000 D
b101 C
b10100 B
b0 A
b101 @
b101 ?
b111100110011001100 =
b101011001100110011 <
b10110011001100110 ;
b100000000000000000 :
b10100110011001101 9
b11100110011001100 8
07
16
b101 5
04
b10110011001100110 3
b100000000000000000 2
b101 1
b10100110011001101 0
b11100110011001100 /
b1000 .
b100000 -
b0 +
b111100110011001100 *
b101011001100110011 )
0(
b101 '
b1010001111010110111 &
b11111111111111100011100001010011 %
b110010010000111100 $
b10100 #
b11111111111111111100110011001100 "
b11111111111111111110011001100111 !
$end
#5000
14
#10000
04
#15000
14
#20000
04
06
#25000
14
#30000
04
#35000
14
#40000
04
#45000
14
#50000
04
#55000
14
#60000
04
17
#65000
b1 _
14
#70000
04
#75000
b10 _
b1000 e
14
#80000
04
#85000
b1011010100000110 F
b1011010100000110 ~
1{
b1011010100000110 |
b0 }
b111 !"
b1010001001100001110110010100000000000 x
b100010110000 y
b1011010100000100 E
b1011010100000100 I"
1F"
b0 H"
b111 J"
b10011000001110111011101110101100000000000 D"
b11011010010 E"
b1011010100000100 G"
b1100100100001110 Z
b1100100100001110 v
b1100100100001110 B"
b110010010000111100 ^
b1000 i
b100 g
14
#90000
04
#95000
b11111111111111110100101011111100 M
b11111111111111110100101011111100 /"
b1011010100000110 L
b1011010100000110 ."
14
b10000000000000000 P
b10000000000000000 n
b0 m
b0 Q
b0 o
b0 l
b10000000000000000 G
b10000000000000000 O"
b0 N"
b0 H
b0 P"
b0 M"
b100 c
b100 q
b10000000000000000 k
b0 j
b10000000000000000 L"
b0 K"
b0 f
b0 d
b10000000000000000 Y
b10000000000000000 '"
b10000000000000000 4"
b1111111111111111111111111111111101001010111111001000000000000000 ,"
b1111111111111111111111111111111101001010111111000000000000000000 -"
b11111111111111110100101011111100 \
b11111111111111110100101011111100 ("
b10110101000001101000000000000000 *"
b10110101000001100000000000000000 +"
b1011010100000110 ]
b1011010100000110 )"
#100000
04
#105000
b10000000000000000 J
b10000000000000000 9"
b0 K
b0 :"
14
b100000000000000001000000000000000 5"
b100000000000000000000000000000000 6"
b1000000000000000 7"
b0 8"
b0 `
b0 1"
b10000000000000000 a
b10000000000000000 2"
#110000
04
#115000
14
#120000
04
#125000
14
b100000000000000000 P
b100000000000000000 n
b10000000000000000 m
b0 G
b0 O"
b10000000000000000 N"
#130000
04
#135000
b11111111111111110100101011111100 K
b11111111111111110100101011111100 :"
b11 L
b11 ."
b11111111111111110000000000000000 M
b11111111111111110000000000000000 /"
b1011010100000110 J
b1011010100000110 9"
14
b0 m
b0 N"
b101 c
b101 q
b1 d
b1111111111111111111111111111111101001010111111001000000000000000 7"
b1111111111111111111111111111111101001010111111000000000000000000 8"
b11111111111111110100101011111100 X
b11111111111111110100101011111100 &"
b11111111111111110100101011111100 3"
b110101010000010100 *"
b101101010000010100 +"
b1111111111111111111111111111111100000000000000000101101111010000 ,"
b1111111111111111111111111111111011111111111111111101101111010000 -"
b10110101000001101000000000000000 5"
b10110101000001100000000000000000 6"
b1011010100000110 Y
b1011010100000110 '"
b1011010100000110 4"
b10000000000000000 P
b10000000000000000 n
b10000000000000000 k
b0 Q
b0 o
b0 j
b10000000000000000 G
b10000000000000000 O"
b10000000000000000 L"
b0 H
b0 P"
b0 K"
b1 f
#140000
04
#145000
14
#150000
04
#155000
14
#160000
04
#165000
14
b11011010100000110 P
b11011010100000110 n
b1011010100000110 m
b100101011111010 G
b100101011111010 O"
b1011010100000110 N"
#170000
04
#175000
b11111111111111110000000000000000 K
b11111111111111110000000000000000 :"
b11111111111111110100101011111110 L
b11111111111111110100101011111110 ."
b11111111111111110100101011111000 M
b11111111111111110100101011111000 /"
b11 J
b11 9"
14
b0 m
b0 N"
b110 c
b110 q
b10 d
b1111111111111111111111111111111100000000000000001000000000000000 7"
b1111111111111111111111111111111100000000000000000000000000000000 8"
b11111111111111110000000000000000 X
b11111111111111110000000000000000 &"
b11111111111111110000000000000000 3"
b1111111111111111111111111111111101001010111111101001111100010010 *"
b1111111111111111111111111111111101001010111111100001111100010010 +"
b1111111111111111111111111111111101001010111110000110000011110100 ,"
b1111111111111111111111111111111101001010111101111110000011110100 -"
b111000000000000000 5"
b110000000000000000 6"
b11 Y
b11 '"
b11 4"
b10000000000000000 P
b10000000000000000 n
b10000000000000000 k
b0 j
b10000000000000000 G
b10000000000000000 O"
b10000000000000000 L"
b0 K"
b10 f
b0 Q
b0 o
b0 l
b0 H
b0 P"
b0 M"
#180000
04
#185000
14
#190000
04
#195000
14
#200000
04
#205000
14
b10000000000000011 P
b10000000000000011 n
b11 m
b1111111111111101 G
b1111111111111101 O"
b11 N"
#210000
04
