sin.v
`ifndef SIN_V
`define SIN_V

module sin_fixed #(
    parameter ITER = 30  // 可選項數，建議不要超過 100
)(
    input  wire signed [31:0] x,   // Q16.16 格式輸入
    output reg  signed [31:0] y    // Q16.16 格式輸出 sin(x)
);

    integer i;
    reg signed [63:0] term;
    reg signed [63:0] num;         // x^n（分子）
    reg signed [63:0] factorial;   // n!（分母）
    reg signed [63:0] sum;
    reg sign;

    always @(*) begin
        sum = x;         // sin(x) = x - x³/3! + x⁵/5! - ...
        sign = 1'b1;     // 下一項是 -x³/3!
        num = (x * x) >>> 16;       // x²
        num = (num * x) >>> 16;     // x³
        factorial = 64'd6;          // 3!

        for (i = 1; i < ITER; i = i + 1) begin
            term = num / factorial;

            if (sign)
                sum = sum - term;
            else
                sum = sum + term;

            // num = num * x²
            num = (num * ((x * x) >>> 16)) >>> 16;

            // factorial *= (2i+2)(2i+3)
            factorial = factorial * (2 * i + 2);
            factorial = factorial * (2 * i + 3);

            sign = ~sign;
        end

        y = sum[31:0];  // 回傳 Q16.16 格式
    end

endmodule

`endif

cos.v
`ifndef COS_V
`define COS_V

module cos_fixed #(
    parameter ITER = 5 // 建議不要超過 100，避免溢位和過度延遲
)(
    input  wire signed [31:0] x,   // Q16.16 弧度輸入
    output reg  signed [31:0] y    // Q16.16 cos(x)
);

    integer i;
    reg signed [63:0] term;
    reg signed [63:0] num;         // 分子 x^n
    reg signed [63:0] factorial;   // 分母 n!
    reg signed [63:0] one;         // 1.0 (Q16.16)
    reg signed [63:0] sum;
    reg sign;

    always @(*) begin
        one = 64'sd1 << 16;
        sum = one;      // y = 1
        sign = 1'b1;    // 第一個項是 -x²/2!
        num = (x * x) >> 16;  // x²
        factorial = 64'd2;
        //$display(" x_input=%0f",  x);
        for (i = 1; i < ITER; i = i + 1) begin
            term = num / factorial;

            if (sign)
                sum = sum - term;
            else
                sum = sum + term;

            // 更新下一項：num = num * x² (Q16.16)
            num = (num * ((x * x) >>> 16)) >>> 16;

            // 更新 factorial：n *= (2i+1)(2i+2)
            factorial = factorial * (2 * i + 1);
            factorial = factorial * (2 * i + 2);

            sign = ~sign;
        end

        y = sum[31:0];  // 轉回 Q16.16 結果
    end

endmodule

`endif

bit_reverse.v
`ifndef BIT_REVERSE_V
`define BIT_REVERSE_V
`define WIDTH 32

module bit_reverse #(parameter w = `WIDTH)(
    input  wire [31:0] b,
    input  wire [31:0] m,
    output reg  [31:0] result
);

    integer i;  // 用 integer 比 reg signed 更標準

    always @(*) begin
        result = 0;
        for (i = 0; i < m; i = i + 1)
            result = result | ((b[i]) << ((m - 1) - i));
    end

endmodule
`endif

pi.v
`ifndef PI_V
`define PI_V
`define WIDTH 32

	module pi 
		#(parameter w=`WIDTH)
		(
			output reg[w-1:0] pi
		);
		
		reg signed [31:0]sign;//sign need array
		reg signed [31:0] i;
		reg signed [31:0] iter;
		reg signed [31:0] domin;
	
		initial begin
			sign=1;
			i=0;
			iter=2000;
			pi = (1 << 16);  // 正確，表示 1.0 in Q16.16
			domin=1;
			while(i <iter) begin
				domin=domin+2;
				sign=-sign;
				pi=pi+sign*((1<<<16)/domin);
				i=i+1;
			end
			pi=pi*4;
		end
	endmodule
`endif

log2.v
`ifndef LOG2_V
`define LOG2_V
`define WIDTH 32
 module log2
 	#(parameter W=`WIDTH)
 	(
 		input wire [W-1:0] N_in,
 		output reg [W-1:0] log2
  
 	);
	reg [W-1:0] N; 
	always @(*) begin
		N=N_in;
		log2=0;
		while(N>>1) begin
			N=N>>1;
			log2 = log2 + 1;
		end
	end
 endmodule  
`endif

complex.v
	// =====================================================
	// complex.v  (Verilog-2001)
	//   - complex_add : (a_re + jb_im) + (c_re + jd_im)
	//   - complex_mul : (a + jb) × (c + jd)
	// -----------------------------------------------------
	// ★ 整數定點示例：   WIDTH = 16 → Q15.0
	//   要用浮點(IP)時，把乘法換成 fp_multiplier 即可
	// =====================================================

	`ifndef COMPLEX_V
	`define COMPLEX_V

	// ---------- 可調參數 -----------------
	`define WIDTH 32               // 單一實、虛部位寬

	// ---------- 加法 ---------------------
	module complex_add
	#(parameter W=`WIDTH)
	(
	    input  signed [W-1:0] a_re, a_im,
	    input  signed [W-1:0] b_re, b_im,
	    output signed [W-1:0] c_re, c_im
	);
	    assign c_re = a_re + b_re;
	    assign c_im = a_im + b_im;
	endmodule

	//-----------sub-----------------------
	module complex_sub
	#(parameter W=`WIDTH)
	(
	    input  signed [W-1:0] a_re, a_im,
	    input  signed [W-1:0] b_re, b_im,
	    output signed [W-1:0] c_re, c_im
	);
	    assign c_re = a_re -b_re;
	    assign c_im = a_im - b_im;
	endmodule
	// ---------- 乘法 ---------------------
	// re = ar*br - ai*bi
	// im = ar*bi + ai*br
	// ------------------------ complex_mul ------------------------
	module complex_mul #(parameter W = 32)(
	    input  signed [W-1:0] a_re, a_im,
	    input  signed [W-1:0] b_re, b_im,
	    output signed [W-1:0] c_re,
	    output signed [W-1:0] c_im
	);
	    // 乘完先保持 64bit 精度
	wire signed [63:0] p_re = a_re * b_re - a_im * b_im;
	wire signed [63:0] p_im = a_re * b_im + a_im * b_re;
	
    	    // Q16.16 → 回到原位寬，這裡做四捨五入
	wire signed [63:0] p_re_rnd = p_re + 32'sd32768;   // +0.5
    	wire signed [63:0] p_im_rnd = p_im + 32'sd32768;

    	assign c_re = p_re_rnd[47:16];  // >>16（取 31..16）
    	assign c_im = p_im_rnd[47:16];
endmodule


	`endif

fft.v
//=============================
// fft.v
//=============================
`ifndef FFT_V
`define FFT_V
`timescale 1ns/1ps

`include "complex.v"
`include "log2.v"
`include "pi.v"
`include "bit_reverse.v"
`include "sin.v"
`include "cos.v"

`define WIDTH 32

module fft #(parameter w=`WIDTH) (
    input wire clk,
    input wire rst,
    input wire start,
    input wire [31:0] x_Re[0:7],
    input wire [31:0] x_Im[0:7],
    input wire [31:0] N,
    output reg [31:0] FFT,
    output reg done
);
    integer k, i, j, b;
    reg signed [31:0] Theta_T,Theta_T1, phi_T_Re, phi_T_Im, T_Re, T_Im, temp_Re, temp_Im;
    reg signed [31:0] x_Re_reg[0:7];
    reg signed [31:0] x_Im_reg[0:7];
    reg signed [31:0] pi_D;
    	

    integer ii,a, m, n;

    wire  signed[31:0] y_cos1, y_sin1;
    wire signed [31:0] add_Re, add_Im, sub_Re, sub_Im;
    wire  signed[31:0] mul1_Re, mul1_Im, mul2_Re, mul2_Im;
    wire signed [31:0] log2_out, pi_out, bit_reverse_out;

    reg [3:0] state;
    localparam IDLE=0, LOAD=1, CALC=2, DONE=3;

    complex_add u_add(.a_re(x_Re_reg[j]), .a_im(x_Im_reg[j]),
                      .b_re(x_Re_reg[b]), .b_im(x_Im_reg[b]),
                      .c_re(add_Re), .c_im(add_Im));
    complex_sub u_sub(.a_re(x_Re_reg[j]), .a_im(x_Im_reg[j]),
                      .b_re(x_Re_reg[b]), .b_im(x_Im_reg[b]),
                      .c_re(sub_Re), .c_im(sub_Im));
    complex_mul u_mul1(.a_re(T_Re), .a_im(T_Im),
                       .b_re(phi_T_Re), .b_im(phi_T_Im),
                       .c_re(mul1_Re), .c_im(mul1_Im));
    complex_mul u_mul2(.a_re(temp_Re), .a_im(temp_Im),
                       .b_re(T_Re), .b_im(T_Im),
                       .c_re(mul2_Re), .c_im(mul2_Im));
    log2 u_log(.N_in(N), .log2(log2_out));
    pi u_pi(.pi(pi_out));
    bit_reverse u_bit_reverse(.b(b), .m(m), .result(bit_reverse_out));
    cos_fixed u_cos1(.x(Theta_T), .y(y_cos1));
    sin_fixed u_sin2(.x(Theta_T), .y(y_sin1));

    always @(posedge clk or posedge rst) begin
        if (rst) begin
             done <= 0;
             FFT <= 0;
             state <= IDLE;
             pi_D = 0;
             m=0;
             Theta_T =0;
             Theta_T1 =0;
             phi_T_Re=0;
             phi_T_Im=0;	
             T_Re=1;
             T_Im=0;
        end else begin
            case (state)
                IDLE: if (start) begin
                	 state <= LOAD;
			 	
             		end
                LOAD: begin
                    for (ii = 0; ii < 8; ii = ii + 1) begin
                        x_Re_reg[ii] = x_Re[ii];
                        x_Im_reg[ii] = x_Im[ii];
                        //$display(" input_x_Re=%0f",  x_Re_reg[ii] );
                       // $display(" input_x_Im=%0f",  x_Im_reg[ii] );
                    end
                    state <= CALC;
                end

                CALC: begin
                    k = N;
                     	//$display("start");
                     	//$display("statte=%0d",state);
                    while (k > 1) begin
                    	
                    	//$display("pi_out=%0f", pi_out/65536.0	);
                        //$display("N=%0f", N );
                        
                       
		
                        n = k;
                        k = k >> 1;
                        pi_D=pi_out;
                        //$display("pi_D=%0f", pi_D/65536.0);
                        Theta_T= (pi_out) *2.0/ N;
		        #10
                        //$display("Theta_T = %0f", Theta_T / 65536.0);
	    		
                        phi_T_Re = y_cos1;
                        phi_T_Im = -y_sin1;
                        //$display(" phi_T_Re=%0f",  phi_T_Re/65536.0);
                        //$display(" phi_T_Im=%0f",  phi_T_Im/65536.0);
                        T_Re=32'sd65536;//65536.0
                        T_Im=32'sd0;
                        //$display(" T_Re2=%0f",  T_Re);
			//$display(" T_Im2=%0f",  T_Im);
                        for (i = 0; i < k; i = i + 1) begin
                            for (j = i; j < N; j = j + n) begin
                                b = j + k;
                                #10
                                temp_Re = sub_Re;
                                temp_Im = sub_Im;
                                
                   		//$display("sub temp_Re=%0f,temp_Im=%0f", temp_Re/65536.0,temp_Im/65536.0);
		      		
		      		#10
                                x_Re_reg[j] = add_Re;
                                x_Im_reg[j] = add_Im;
                                
                   		//$display("add x_Re_reg[%0d]=%0f,x_Im_reg[%0d]=%0f",j,   x_Re_reg[j]/65536.0,j,x_Im_reg[j]/65536.0);
		      		
		      		#10
                                x_Re_reg[b] = mul2_Re;
                                #10
                                x_Im_reg[b] = mul2_Im;
                                
                   		//$display("mul x_Re_reg[%0d]=%0f,x_Im_reg[%0d]=%0f",b,   x_Re_reg[b]/65536.0,b,x_Im_reg[b]/65536.0);
		      	
                            end
                            T_Re = mul1_Re;                            
                            T_Im = mul1_Im;
                            //$display(" fin_Re=%0f,fin_Im=%0f",   T_Re/65536.0,T_Im/65536.0);
			   
                        end
                        m = log2_out;
                        #10
                        //$display(" m=%0f", m);
                        for (a = 0; a < N; a = a + 1) begin
                            b=a;
                        #10
                            b = bit_reverse_out;
                            	
		    	    
                        #10
                            if (b > a) begin
                                temp_Re = x_Re_reg[a];                                
                                temp_Im = x_Im_reg[a];                                
                                x_Re_reg[a] = x_Re_reg[b];
                                x_Im_reg[a] = x_Im_reg[b];                                
                                x_Re_reg[b] = temp_Re;                              
                                x_Im_reg[b] = temp_Im;
                            end
                        end
                    end
                    for(i=0;i<N;i++) begin
                    $display(" final: x_Re_reg[%0d]=%0f,x_Im_reg[%0d]=%0f",i,   x_Re_reg[i]/65536.0,i,x_Im_reg[i]/65536.0);
		
		    end
		    #10
                    FFT <= x_Re_reg[0];
                    done <= 1;
                    state <= DONE;
                end

                DONE: ; // 保持狀態直到重置
            endcase
        end
    end
endmodule

`endif

complex_tb.v
`timescale 1ns/1ps
`include "complex.v"
`include "log2.v"
`include "pi.v"
`include "bit_reverse.v"
`include "fft.v"
`include "cos.v"
`include "sin.v"

module complex_tb;
    parameter NUM = 8;

    // 基本變數
    reg  signed [31:0] a_re, a_im, b_re, b_im;
    reg  [31:0] N;
    wire [31:0] log2;
    wire [31:0] pi;
    wire signed [31:0] add_re, add_im;
    wire signed [31:0] sub_re, sub_im;
    wire signed [31:0] mul_re, mul_im;
    reg  [31:0] b, m;
    wire [31:0] result;

    // Cos/Sin 測試
    reg signed [31:0] x;             // Q16.16
    wire signed [31:0] y_cos, y_sin; // Q16.16 輸出
    localparam signed [31:0] Q2   = 32'sd131072; // 2.0
    // FFT 測試
    reg clk = 0;
    reg rst;
    reg start;
    reg [31:0] x_Re[0:NUM-1];
    reg [31:0] x_Im[0:NUM-1];
    reg [31:0] N_fft;
    wire [31:0] FFT;
    wire done;

    // 時脈產生 (100 MHz)i
    always #5 clk = ~clk;
	
    // === 模組例化 ===
    complex_add u_add(.a_re(a_re), .a_im(a_im), .b_re(b_re), .b_im(b_im), .c_re(add_re), .c_im(add_im));
    complex_sub u_sub(.a_re(a_re), .a_im(a_im), .b_re(b_re), .b_im(b_im), .c_re(sub_re), .c_im(sub_im));
    complex_mul u_mul(.a_re(a_re), .a_im(a_im), .b_re(b_re), .b_im(b_im), .c_re(mul_re), .c_im(mul_im));
    log2        u_log(.N_in(N), .log2(log2));
    pi          u_pi(.pi(pi));
    bit_reverse u_bit_reverse(.b(b), .m(m), .result(result));
    //cos_fixed   u_cos(.x(x), .y(y_cos));
    //sin_fixed   u_sin(.x(x), .y(y_sin));

    fft u_fft(
        .clk(clk), .rst(rst), .start(start),
        .x_Re(x_Re), .x_Im(x_Im), .N(N_fft),
        .FFT(FFT), .done(done)
    );

    // === test bench ===
    initial begin
        $dumpfile("wave.vcd");
        $dumpvars(0, complex_tb);

        // === complex unit ===
        a_re = 	32'sd85197; a_im = 32'sd117964 ;   // 3 + j4
        b_re = 	32'sd91750 ; b_im = 32'sd131072 ;   // 1 + j2
        b = 32'd5; m = 32'd5;
        N = 32'd32;

        // === FFT data output ===
        x_Re[0] = 32'sd65536;  x_Re[1] = 32'sd65536;
        x_Re[2] = 32'sd65536; x_Re[3] = 32'sd65536;
        x_Re[4] = 32'sd0;        x_Re[5] = 32'sd0;
        x_Re[6] = 32'sd0;        x_Re[7] = 32'sd0;

        x_Im[0] = 32'sd0; x_Im[1] =32'sd0; x_Im[2] = 32'sd0; x_Im[3] =32'sd0;
        x_Im[4] = 32'sd0; x_Im[5] =32'sd0; x_Im[6] = 32'sd0; x_Im[7] = 32'sd0;

        // === control FFT ===
        N_fft = 32'sd8;
        rst = 1; start = 0;
        #20 rst = 0;
        #40 start = 1;

        // === test cos/sin ===
        //x = 32'sd51472; // 約等於 pi/3 ≈ 1.57 rad ≈ Q16.16 = 0x19220

        wait(done); // 等 FFT 完成

        // === show single module===
        //$display("FFT result: %d", FFT);
        //$display("ADD: (%0f , %0f)", add_re/65536.0, add_im/65536.0);
        //$display("SUB: (%0f , %0f)", sub_re/65536.0, sub_im/65536.0);
      	//$display("MUL: (%0f , %0f)", $itor(mul_re) / 65536.0,$itor(mul_im) / 65536.0);

        //$display("log(%0d) = %0d", N, log2);
        //$display("π (Q16.16) raw = %0d", pi);
        //$display("π ≈ %f", pi / 65536.0);
        //$display("bit reverse: %0f", result);
        //  $display("cos(%f) ≈ %f", x / 65536.0, y_cos / 65536.0);
        //$display("sin(%f) ≈ %f", x / 65536.0, y_sin / 65536.0);

        #100 $finish;
    end
endmodule

wave.vcd
$date
	Tue May 13 00:24:56 2025
$end
$version
	Icarus Verilog
$end
$timescale
	1ps
$end
$scope module complex_tb $end
$var wire 32 ! sub_re [31:0] $end
$var wire 32 " sub_im [31:0] $end
$var wire 32 # result [31:0] $end
$var wire 32 $ pi [31:0] $end
$var wire 32 % mul_re [31:0] $end
$var wire 32 & mul_im [31:0] $end
$var wire 32 ' log2 [31:0] $end
$var wire 1 ( done $end
$var wire 32 ) add_re [31:0] $end
$var wire 32 * add_im [31:0] $end
$var wire 32 + FFT [31:0] $end
$var parameter 32 , NUM $end
$var parameter 32 - Q2 $end
$var reg 32 . N [31:0] $end
$var reg 32 / N_fft [31:0] $end
$var reg 32 0 a_im [31:0] $end
$var reg 32 1 a_re [31:0] $end
$var reg 32 2 b [31:0] $end
$var reg 32 3 b_im [31:0] $end
$var reg 32 4 b_re [31:0] $end
$var reg 1 5 clk $end
$var reg 32 6 m [31:0] $end
$var reg 1 7 rst $end
$var reg 1 8 start $end
$scope module u_add $end
$var wire 32 9 a_im [31:0] $end
$var wire 32 : a_re [31:0] $end
$var wire 32 ; b_im [31:0] $end
$var wire 32 < b_re [31:0] $end
$var wire 32 = c_re [31:0] $end
$var wire 32 > c_im [31:0] $end
$var parameter 32 ? W $end
$upscope $end
$scope module u_bit_reverse $end
$var wire 32 @ b [31:0] $end
$var wire 32 A m [31:0] $end
$var parameter 32 B w $end
$var reg 32 C result [31:0] $end
$var integer 32 D i [31:0] $end
$upscope $end
$scope module u_fft $end
$var wire 32 E N [31:0] $end
$var wire 1 5 clk $end
$var wire 1 7 rst $end
$var wire 1 8 start $end
$var wire 32 F y_sin1 [31:0] $end
$var wire 32 G y_cos1 [31:0] $end
$var wire 32 H sub_Re [31:0] $end
$var wire 32 I sub_Im [31:0] $end
$var wire 32 J pi_out [31:0] $end
$var wire 32 K mul2_Re [31:0] $end
$var wire 32 L mul2_Im [31:0] $end
$var wire 32 M mul1_Re [31:0] $end
$var wire 32 N mul1_Im [31:0] $end
$var wire 32 O log2_out [31:0] $end
$var wire 32 P bit_reverse_out [31:0] $end
$var wire 32 Q add_Re [31:0] $end
$var wire 32 R add_Im [31:0] $end
$var parameter 32 S CALC $end
$var parameter 32 T DONE $end
$var parameter 32 U IDLE $end
$var parameter 32 V LOAD $end
$var parameter 32 W w $end
$var reg 32 X FFT [31:0] $end
$var reg 32 Y T_Im [31:0] $end
$var reg 32 Z T_Re [31:0] $end
$var reg 32 [ Theta_T [31:0] $end
$var reg 32 \ Theta_T1 [31:0] $end
$var reg 1 ( done $end
$var reg 32 ] phi_T_Im [31:0] $end
$var reg 32 ^ phi_T_Re [31:0] $end
$var reg 32 _ pi_D [31:0] $end
$var reg 4 ` state [3:0] $end
$var reg 32 a temp_Im [31:0] $end
$var reg 32 b temp_Re [31:0] $end
$var integer 32 c a [31:0] $end
$var integer 32 d b [31:0] $end
$var integer 32 e i [31:0] $end
$var integer 32 f ii [31:0] $end
$var integer 32 g j [31:0] $end
$var integer 32 h k [31:0] $end
$var integer 32 i m [31:0] $end
$var integer 32 j n [31:0] $end
$scope module u_add $end
$var wire 32 k a_im [31:0] $end
$var wire 32 l a_re [31:0] $end
$var wire 32 m b_im [31:0] $end
$var wire 32 n b_re [31:0] $end
$var wire 32 o c_re [31:0] $end
$var wire 32 p c_im [31:0] $end
$var parameter 32 q W $end
$upscope $end
$scope module u_bit_reverse $end
$var wire 32 r b [31:0] $end
$var wire 32 s m [31:0] $end
$var parameter 32 t w $end
$var reg 32 u result [31:0] $end
$var integer 32 v i [31:0] $end
$upscope $end
$scope module u_cos1 $end
$var wire 32 w x [31:0] $end
$var parameter 32 x ITER $end
$var reg 64 y factorial [63:0] $end
$var reg 64 z num [63:0] $end
$var reg 64 { one [63:0] $end
$var reg 1 | sign $end
$var reg 64 } sum [63:0] $end
$var reg 64 ~ term [63:0] $end
$var reg 32 !" y [31:0] $end
$var integer 32 "" i [31:0] $end
$upscope $end
$scope module u_log $end
$var wire 32 #" N_in [31:0] $end
$var parameter 32 $" W $end
$var reg 32 %" N [31:0] $end
$var reg 32 &" log2 [31:0] $end
$upscope $end
$scope module u_mul1 $end
$var wire 32 '" a_im [31:0] $end
$var wire 32 (" a_re [31:0] $end
$var wire 32 )" b_im [31:0] $end
$var wire 32 *" b_re [31:0] $end
$var wire 64 +" p_re_rnd [63:0] $end
$var wire 64 ," p_re [63:0] $end
$var wire 64 -" p_im_rnd [63:0] $end
$var wire 64 ." p_im [63:0] $end
$var wire 32 /" c_re [31:0] $end
$var wire 32 0" c_im [31:0] $end
$var parameter 32 1" W $end
$upscope $end
$scope module u_mul2 $end
$var wire 32 2" a_im [31:0] $end
$var wire 32 3" a_re [31:0] $end
$var wire 32 4" b_im [31:0] $end
$var wire 32 5" b_re [31:0] $end
$var wire 64 6" p_re_rnd [63:0] $end
$var wire 64 7" p_re [63:0] $end
$var wire 64 8" p_im_rnd [63:0] $end
$var wire 64 9" p_im [63:0] $end
$var wire 32 :" c_re [31:0] $end
$var wire 32 ;" c_im [31:0] $end
$var parameter 32 <" W $end
$upscope $end
$scope module u_pi $end
$var parameter 32 =" w $end
$var reg 32 >" domin [31:0] $end
$var reg 32 ?" i [31:0] $end
$var reg 32 @" iter [31:0] $end
$var reg 32 A" pi [31:0] $end
$var reg 32 B" sign [31:0] $end
$upscope $end
$scope module u_sin2 $end
$var wire 32 C" x [31:0] $end
$var parameter 32 D" ITER $end
$var reg 64 E" factorial [63:0] $end
$var reg 64 F" num [63:0] $end
$var reg 1 G" sign $end
$var reg 64 H" sum [63:0] $end
$var reg 64 I" term [63:0] $end
$var reg 32 J" y [31:0] $end
$var integer 32 K" i [31:0] $end
$upscope $end
$scope module u_sub $end
$var wire 32 L" a_im [31:0] $end
$var wire 32 M" a_re [31:0] $end
$var wire 32 N" b_im [31:0] $end
$var wire 32 O" b_re [31:0] $end
$var wire 32 P" c_re [31:0] $end
$var wire 32 Q" c_im [31:0] $end
$var parameter 32 R" W $end
$upscope $end
$upscope $end
$scope module u_log $end
$var wire 32 S" N_in [31:0] $end
$var parameter 32 T" W $end
$var reg 32 U" N [31:0] $end
$var reg 32 V" log2 [31:0] $end
$upscope $end
$scope module u_mul $end
$var wire 32 W" a_im [31:0] $end
$var wire 32 X" a_re [31:0] $end
$var wire 32 Y" b_im [31:0] $end
$var wire 32 Z" b_re [31:0] $end
$var wire 64 [" p_re_rnd [63:0] $end
$var wire 64 \" p_re [63:0] $end
$var wire 64 ]" p_im_rnd [63:0] $end
$var wire 64 ^" p_im [63:0] $end
$var wire 32 _" c_re [31:0] $end
$var wire 32 `" c_im [31:0] $end
$var parameter 32 a" W $end
$upscope $end
$scope module u_pi $end
$var parameter 32 b" w $end
$var reg 32 c" domin [31:0] $end
$var reg 32 d" i [31:0] $end
$var reg 32 e" iter [31:0] $end
$var reg 32 f" pi [31:0] $end
$var reg 32 g" sign [31:0] $end
$upscope $end
$scope module u_sub $end
$var wire 32 h" a_im [31:0] $end
$var wire 32 i" a_re [31:0] $end
$var wire 32 j" b_im [31:0] $end
$var wire 32 k" b_re [31:0] $end
$var wire 32 l" c_re [31:0] $end
$var wire 32 m" c_im [31:0] $end
$var parameter 32 n" W $end
$upscope $end
$upscope $end
$enddefinitions $end
$comment Show the parameter values. $end
$dumpall
b100000 n"
b100000 b"
b100000 a"
b100000 T"
b100000 R"
b11110 D"
b100000 ="
b100000 <"
b100000 1"
b100000 $"
b101 x
b100000 t
b100000 q
b100000 W
b1 V
b0 U
b11 T
b10 S
b100000 B
b100000 ?
b100000000000000000 -
b1000 ,
$end
#0
$dumpvars
b11111111111111111100110011001100 m"
b11111111111111111110011001100111 l"
b10110011001100110 k"
b100000000000000000 j"
b10100110011001101 i"
b11100110011001100 h"
b1 g"
b110010010000111100 f"
b11111010000 e"
b11111010000 d"
b111110100001 c"
b1010001111010110111 `"
b11111111111111100011100001010011 _"
b10100011110101101101110000101001000 ^"
b10100011110101101110110000101001000 ]"
b1111111111111111111111111111111000111000010100110100011110101110 \"
b1111111111111111111111111111111000111000010100111100011110101110 ["
b10110011001100110 Z"
b100000000000000000 Y"
b10100110011001101 X"
b11100110011001100 W"
b101 V"
b1 U"
b100000 S"
bx Q"
bx P"
bx O"
bx N"
bx M"
bx L"
b11110 K"
b0 J"
b0 I"
b0 H"
0G"
b0 F"
b10101100000000000000000000000000000000000000000000000000000000 E"
b0 C"
b1 B"
b110010010000111100 A"
b11111010000 @"
b11111010000 ?"
b111110100001 >"
bx ;"
bx :"
bx 9"
bx 8"
bx 7"
bx 6"
b1 5"
b0 4"
bx 3"
bx 2"
b0 0"
b0 /"
b0 ."
b1000000000000000 -"
b0 ,"
b1000000000000000 +"
b0 *"
b0 )"
b1 ("
b0 '"
b11 &"
b1 %"
b1000 #"
b101 ""
b10000000000000000 !"
b0 ~
b10000000000000000 }
1|
b10000000000000000 {
b0 z
b1101110101111100000000 y
b0 w
b0 v
b0 u
b0 s
bx r
bx p
bx o
bx n
bx m
bx l
bx k
bx j
b0 i
bx h
bx g
bx f
bx e
bx d
bx c
bx b
bx a
b0 `
b0 _
b0 ^
b0 ]
b0 \
b0 [
b1 Z
b0 Y
b0 X
bx R
bx Q
b0 P
b11 O
b0 N
b0 M
bx L
bx K
b110010010000111100 J
bx I
bx H
b10000000000000000 G
b0 F
b1000 E
b101 D
b10100 C
b101 A
b101 @
b111100110011001100 >
b101011001100110011 =
b10110011001100110 <
b100000000000000000 ;
b10100110011001101 :
b11100110011001100 9
08
17
b101 6
05
b10110011001100110 4
b100000000000000000 3
b101 2
b10100110011001101 1
b11100110011001100 0
b1000 /
b100000 .
b0 +
b111100110011001100 *
b101011001100110011 )
0(
b101 '
b1010001111010110111 &
b11111111111111100011100001010011 %
b110010010000111100 $
b10100 #
b11111111111111111100110011001100 "
b11111111111111111110011001100111 !
$end
#5000
15
#10000
05
#15000
15
#20000
05
07
#25000
15
#30000
05
#35000
15
#40000
05
#45000
15
#50000
05
#55000
15
#60000
05
18
#65000
b1 `
15
#70000
05
#75000
b10 `
b1000 f
15
#80000
05
#85000
b1011010100000101 G
b1011010100000101 !"
1|
b1011010100000101 }
b0 ~
b101 ""
b1101110101111100000000 y
b1011011011011 z
b1011010100000101 F
b1011010100000101 J"
b0 I"
b11110 K"
b10101100000000000000000000000000000000000000000000000000000000 E"
b0 F"
0G"
b1011010100000101 H"
b1100100100001111 [
b1100100100001111 w
b1100100100001111 C"
b110010010000111100 _
b1000 j
b100 h
15
#90000
05
#95000
b11111111111111110100101011111011 N
b11111111111111110100101011111011 0"
b1011010100000101 M
b1011010100000101 /"
15
b10000000000000000 Q
b10000000000000000 o
b0 n
b0 R
b0 p
b0 m
b10000000000000000 H
b10000000000000000 P"
b0 O"
b0 I
b0 Q"
b0 N"
b100 d
b100 r
b10000000000000000 l
b0 k
b10000000000000000 M"
b0 L"
b0 g
b0 e
b10000000000000000 Z
b10000000000000000 ("
b10000000000000000 5"
b1111111111111111111111111111111101001010111110111000000000000000 -"
b1111111111111111111111111111111101001010111110110000000000000000 ."
b11111111111111110100101011111011 ]
b11111111111111110100101011111011 )"
b10110101000001011000000000000000 +"
b10110101000001010000000000000000 ,"
b1011010100000101 ^
b1011010100000101 *"
#100000
05
#105000
b10000000000000000 K
b10000000000000000 :"
b0 L
b0 ;"
15
b100000000000000001000000000000000 6"
b100000000000000000000000000000000 7"
b1000000000000000 8"
b0 9"
b0 a
b0 2"
b10000000000000000 b
b10000000000000000 3"
#110000
05
#115000
15
#120000
05
#125000
15
b100000000000000000 Q
b100000000000000000 o
b10000000000000000 n
b0 H
b0 P"
b10000000000000000 O"
#130000
05
#135000
b11111111111111110100101011111011 L
b11111111111111110100101011111011 ;"
b0 M
b0 /"
b11111111111111110000000000000000 N
b11111111111111110000000000000000 0"
b1011010100000101 K
b1011010100000101 :"
15
b0 n
b0 O"
b101 d
b101 r
b1 e
b1111111111111111111111111111111101001010111110111000000000000000 8"
b1111111111111111111111111111111101001010111110110000000000000000 9"
b11111111111111110100101011111011 Y
b11111111111111110100101011111011 '"
b11111111111111110100101011111011 4"
b1000000000000000 +"
b0 ,"
b1111111111111111111111111111111100000000000000000101101111001110 -"
b1111111111111111111111111111111011111111111111111101101111001110 ."
b10110101000001011000000000000000 6"
b10110101000001010000000000000000 7"
b1011010100000101 Z
b1011010100000101 ("
b1011010100000101 5"
b10000000000000000 Q
b10000000000000000 o
b10000000000000000 l
b0 R
b0 p
b0 k
b10000000000000000 H
b10000000000000000 P"
b10000000000000000 M"
b0 I
b0 Q"
b0 L"
b1 g
#140000
05
#145000
15
#150000
05
#155000
15
#160000
05
#165000
15
b11011010100000101 Q
b11011010100000101 o
b1011010100000101 n
b100101011111011 H
b100101011111011 P"
b1011010100000101 O"
#170000
05
#175000
b11111111111111110000000000000000 L
b11111111111111110000000000000000 ;"
b11111111111111110100101011111011 M
b11111111111111110100101011111011 /"
b11111111111111110100101011111011 N
b11111111111111110100101011111011 0"
b0 K
b0 :"
15
b0 n
b0 O"
b110 d
b110 r
b10 e
b1111111111111111111111111111111100000000000000001000000000000000 8"
b1111111111111111111111111111111100000000000000000000000000000000 9"
b11111111111111110000000000000000 Y
b11111111111111110000000000000000 '"
b11111111111111110000000000000000 4"
b1111111111111111111111111111111101001010111110111000000000000000 +"
b1111111111111111111111111111111101001010111110110000000000000000 ,"
b1111111111111111111111111111111101001010111110111000000000000000 -"
b1111111111111111111111111111111101001010111110110000000000000000 ."
b1000000000000000 6"
b0 7"
b0 Z
b0 ("
b0 5"
b10000000000000000 Q
b10000000000000000 o
b10000000000000000 l
b0 k
b10000000000000000 H
b10000000000000000 P"
b10000000000000000 M"
b0 L"
b10 g
b0 R
b0 p
b0 m
b0 I
b0 Q"
b0 N"
#180000
05
#185000
15
#190000
05
#195000
15
#200000
05
#205000
15
#210000
05
#215000
b11111111111111110100101011111011 L
b11111111111111110100101011111011 ;"
b11111111111111110000000000000000 M
b11111111111111110000000000000000 /"
b0 N
b0 0"
b11111111111111110100101011111011 K
b11111111111111110100101011111011 :"
15
b111 d
b111 r
b11 e
b1111111111111111111111111111111101001010111110111000000000000000 8"
b1111111111111111111111111111111101001010111110110000000000000000 9"
b11111111111111110100101011111011 Y
b11111111111111110100101011111011 '"
b11111111111111110100101011111011 4"
b1111111111111111111111111111111100000000000000000101101111001110 +"
b1111111111111111111111111111111011111111111111111101101111001110 ,"
b1000000000000000 -"
b0 ."
b1111111111111111111111111111111101001010111110111000000000000000 6"
b1111111111111111111111111111111101001010111110110000000000000000 7"
b11111111111111110100101011111011 Z
b11111111111111110100101011111011 ("
b11111111111111110100101011111011 5"
b10000000000000000 Q
b10000000000000000 o
b10000000000000000 l
b0 k
b10000000000000000 H
b10000000000000000 P"
b10000000000000000 M"
b0 L"
b11 g
b0 R
b0 p
b0 m
b0 I
b0 Q"
b0 N"
#220000
05
#225000
15
#230000
05
#235000
15
#240000
05
#245000
15
b100101011111011 Q
b100101011111011 o
b11111111111111110100101011111011 n
b11011010100000101 H
b11011010100000101 P"
b11111111111111110100101011111011 O"
#250000
05
